harlequin_wherobots/__init__.py
harlequin_wherobots/adapter.py
harlequin_wherobots/cli_options.py
harlequin_wherobots-0.9.0.dist-info/METADATA
harlequin_wherobots-0.9.0.dist-info/WHEEL
harlequin_wherobots-0.9.0.dist-info/entry_points.txt
harlequin_wherobots-0.9.0.dist-info/licenses/LICENSE
harlequin_wherobots-0.9.0.dist-info/RECORD
