Metadata-Version: 2.4
Name: harlequin-wherobots
Version: 0.9.0
Summary: Harlequin adapter for Wherobots' Spatial SQL API
Author-email: Maxime Petazzoni <max@wherobots.com>
License-File: LICENSE
Requires-Python: <3.14,>=3.9
Requires-Dist: harlequin
Requires-Dist: packaging>=25.0
Requires-Dist: wherobots-python-dbapi
